<annotation>
  <folder/>
  <filename>IMG_20190715_123426.labeled.jpg</filename>
  <database/>
  <annotation/>
  <image/>
  <size>
    <height>1376</height>
    <width>1024</width>
    <depth>3</depth>
  </size>
  <segmented/>
  <object>
    <name>##</name>
    <pose/>
    <truncated/>
    <difficult/>
    <bndbox>
      <xmin>96.48518371582031</xmin>
      <ymin>89.37186431884766</ymin>
      <xmax>117.21046447753906</xmax>
      <ymax>120.5351333618164</ymax>
    </bndbox>
  </object>
  <object>
    <name>2</name>
    <pose/>
    <truncated/>
    <difficult/>
    <bndbox>
      <xmin>123.63810588695384</xmin>
      <ymin>88.43430978280526</ymin>
      <xmax>146.79208995677806</xmax>
      <ymax>121.58662301522713</ymax>
    </bndbox>
  </object>
  <object>
    <name>8</name>
    <pose/>
    <truncated/>
    <difficult/>
    <bndbox>
      <xmin>153.13329060872397</xmin>
      <ymin>88.40961371527777</ymin>
      <xmax>176.5112508138021</xmax>
      <ymax>121.64063178168402</ymax>
    </bndbox>
  </object>
  <object>
    <name>&#1082;</name>
    <pose/>
    <truncated/>
    <difficult/>
    <bndbox>
      <xmin>95.07852172851562</xmin>
      <ymin>131.50126139322916</ymin>
      <xmax>119.08012390136719</xmax>
      <ymax>168.34386189778647</ymax>
    </bndbox>
  </object>
  <object>
    <name>&#1088;</name>
    <pose/>
    <truncated/>
    <difficult/>
    <bndbox>
      <xmin>122.2808952331543</xmin>
      <ymin>131.34025307880106</ymin>
      <xmax>146.28249740600586</xmax>
      <ymax>168.18285358335837</ymax>
    </bndbox>
  </object>
  <object>
    <name>&#1080;</name>
    <pose/>
    <truncated/>
    <difficult/>
    <bndbox>
      <xmin>150.4190877278646</xmin>
      <ymin>130.5771687825521</ymin>
      <xmax>175.30677286783853</xmax>
      <ymax>168.55536905924478</ymax>
    </bndbox>
  </object>
  <object>
    <name>&#1095;</name>
    <pose/>
    <truncated/>
    <difficult/>
    <bndbox>
      <xmin>178.91246541341147</xmin>
      <ymin>130.4181539093621</ymin>
      <xmax>203.8001505533854</xmax>
      <ymax>168.3963541860548</ymax>
    </bndbox>
  </object>
  <object>
    <name>&#1072;</name>
    <pose/>
    <truncated/>
    <difficult/>
    <bndbox>
      <xmin>206.23856099446616</xmin>
      <ymin>130.26565336444418</ymin>
      <xmax>231.1262461344401</xmax>
      <ymax>168.24385364113687</ymax>
    </bndbox>
  </object>
  <object>
    <name>&#1090;</name>
    <pose/>
    <truncated/>
    <difficult/>
    <bndbox>
      <xmin>234.17422993977866</xmin>
      <ymin>130.10975093322526</ymin>
      <xmax>259.0619150797526</xmax>
      <ymax>168.08795120991795</ymax>
    </bndbox>
  </object>
  <object>
    <name>!</name>
    <pose/>
    <truncated/>
    <difficult/>
    <bndbox>
      <xmin>263.8408559163411</xmin>
      <ymin>129.9441884358724</ymin>
      <xmax>288.7285410563151</xmax>
      <ymax>167.9223887125651</ymax>
    </bndbox>
  </object>
  <object>
    <name>&#1083;</name>
    <pose/>
    <truncated/>
    <difficult/>
    <bndbox>
      <xmin>95.24482981363933</xmin>
      <ymin>226.92865753173828</ymin>
      <xmax>118.42493947347005</xmax>
      <ymax>262.9646224975586</ymax>
    </bndbox>
  </object>
  <object>
    <name>&#1077;</name>
    <pose/>
    <truncated/>
    <difficult/>
    <bndbox>
      <xmin>123.40453211466472</xmin>
      <ymin>226.57827634318824</ymin>
      <xmax>146.58464177449545</xmax>
      <ymax>262.61424130900855</ymax>
    </bndbox>
  </object>
  <object>
    <name>&#1090;</name>
    <pose/>
    <truncated/>
    <difficult/>
    <bndbox>
      <xmin>151.28672790527344</xmin>
      <ymin>226.5479278564453</ymin>
      <xmax>174.3308563232422</xmax>
      <ymax>261.84645080566406</ymax>
    </bndbox>
  </object>
  <object>
    <name>&#1091;</name>
    <pose/>
    <truncated/>
    <difficult/>
    <bndbox>
      <xmin>179.6849365234375</xmin>
      <ymin>226.2541976725485</ymin>
      <xmax>202.72906494140625</xmax>
      <ymax>261.5527206217672</ymax>
    </bndbox>
  </object>
  <object>
    <name>&#1095;</name>
    <pose/>
    <truncated/>
    <difficult/>
    <bndbox>
      <xmin>208.56471252441406</xmin>
      <ymin>225.95548650982255</ymin>
      <xmax>231.6088409423828</xmax>
      <ymax>261.2540094590413</ymax>
    </bndbox>
  </object>
  <object>
    <name>&#1080;</name>
    <pose/>
    <truncated/>
    <difficult/>
    <bndbox>
      <xmin>236.97298431396484</xmin>
      <ymin>225.66165223988205</ymin>
      <xmax>260.0171127319336</xmax>
      <ymax>260.9601751891008</ymax>
    </bndbox>
  </object>
  <object>
    <name>&#1077;</name>
    <pose/>
    <truncated/>
    <difficult/>
    <bndbox>
      <xmin>265.7394714355469</xmin>
      <ymin>225.3641128540039</ymin>
      <xmax>288.7835998535156</xmax>
      <ymax>260.66263580322266</ymax>
    </bndbox>
  </object>
  <object>
    <name>&#1085;</name>
    <pose/>
    <truncated/>
    <difficult/>
    <bndbox>
      <xmin>94.14404169718425</xmin>
      <ymin>320.2572835286458</ymin>
      <xmax>118.10942204793294</xmax>
      <ymax>356.7561442057292</ymax>
    </bndbox>
  </object>
  <object>
    <name>&#1072;</name>
    <pose/>
    <truncated/>
    <difficult/>
    <bndbox>
      <xmin>122.6053949991862</xmin>
      <ymin>320.4268628921819</ymin>
      <xmax>146.5707753499349</xmax>
      <ymax>356.92572356926524</ymax>
    </bndbox>
  </object>
  <object>
    <name>&#1082;</name>
    <pose/>
    <truncated/>
    <difficult/>
    <bndbox>
      <xmin>178.90215174357095</xmin>
      <ymin>320.7622920643844</ymin>
      <xmax>202.86753209431967</xmax>
      <ymax>357.26115274146775</ymax>
    </bndbox>
  </object>
  <object>
    <name>&#1088;</name>
    <pose/>
    <truncated/>
    <difficult/>
    <bndbox>
      <xmin>207.98313013712564</xmin>
      <ymin>320.93556329835053</ymin>
      <xmax>231.94851048787436</xmax>
      <ymax>357.4344239754339</ymax>
    </bndbox>
  </object>
  <object>
    <name>&#1099;</name>
    <pose/>
    <truncated/>
    <difficult/>
    <bndbox>
      <xmin>236.63067499796549</xmin>
      <ymin>321.1062520345052</ymin>
      <xmax>260.5960553487142</xmax>
      <ymax>357.60511271158856</ymax>
    </bndbox>
  </object>
  <object>
    <name>&#1096;</name>
    <pose/>
    <truncated/>
    <difficult/>
    <bndbox>
      <xmin>266.54039510091144</xmin>
      <ymin>322.46493378197147</ymin>
      <xmax>289.9780985514323</xmax>
      <ymax>357.75580699160685</ymax>
    </bndbox>
  </object>
  <object>
    <name>&#1077;</name>
    <pose/>
    <truncated/>
    <difficult/>
    <bndbox>
      <xmin>295.5137227376302</xmin>
      <ymin>322.4853006998698</ymin>
      <xmax>318.95142618815106</xmax>
      <ymax>357.7761739095052</ymax>
    </bndbox>
  </object>
  <object>
    <name>&#1087;</name>
    <pose/>
    <truncated/>
    <difficult/>
    <bndbox>
      <xmin>93.70073699951172</xmin>
      <ymin>416.5140075683594</ymin>
      <xmax>117.01079559326172</xmax>
      <ymax>451.0975646972656</ymax>
    </bndbox>
  </object>
  <object>
    <name>&#1083;</name>
    <pose/>
    <truncated/>
    <difficult/>
    <bndbox>
      <xmin>122.78050231933594</xmin>
      <ymin>416.76378348137143</ymin>
      <xmax>146.09056091308594</xmax>
      <ymax>451.3473406102777</ymax>
    </bndbox>
  </object>
  <object>
    <name>&#1072;</name>
    <pose/>
    <truncated/>
    <difficult/>
    <bndbox>
      <xmin>151.14627075195312</xmin>
      <ymin>417.00742663428633</ymin>
      <xmax>174.45632934570312</xmax>
      <ymax>451.5909837631926</ymax>
    </bndbox>
  </object>
  <object>
    <name>&#1090;</name>
    <pose/>
    <truncated/>
    <difficult/>
    <bndbox>
      <xmin>179.44789123535156</xmin>
      <ymin>417.2505187988281</ymin>
      <xmax>202.75794982910156</xmax>
      <ymax>451.8340759277344</ymax>
    </bndbox>
  </object>
  <object>
    <name>&#1086;</name>
    <pose/>
    <truncated/>
    <difficult/>
    <bndbox>
      <xmin>208.92129516601562</xmin>
      <ymin>417.503675806644</ymin>
      <xmax>232.23135375976562</xmax>
      <ymax>452.0872329355503</ymax>
    </bndbox>
  </object>
  <object>
    <name>&#1095;</name>
    <pose/>
    <truncated/>
    <difficult/>
    <bndbox>
      <xmin>237.9779815673828</xmin>
      <ymin>417.3087440295702</ymin>
      <xmax>261.47198486328125</xmax>
      <ymax>452.96664197878897</ymax>
    </bndbox>
  </object>
  <object>
    <name>&#1082;</name>
    <pose/>
    <truncated/>
    <difficult/>
    <bndbox>
      <xmin>267.0196304321289</xmin>
      <ymin>417.4324922884801</ymin>
      <xmax>290.51363372802734</xmax>
      <ymax>453.09039023769884</ymax>
    </bndbox>
  </object>
  <object>
    <name>&#1072;</name>
    <pose/>
    <truncated/>
    <difficult/>
    <bndbox>
      <xmin>296.1642532348633</xmin>
      <ymin>417.5566793256976</ymin>
      <xmax>319.6582565307617</xmax>
      <ymax>453.21457727491634</ymax>
    </bndbox>
  </object>
  <object>
    <name>&#1084;</name>
    <pose/>
    <truncated/>
    <difficult/>
    <bndbox>
      <xmin>326.28556060791016</xmin>
      <ymin>417.6850280761719</ymin>
      <xmax>349.7795639038086</xmax>
      <ymax>453.3429260253906</ymax>
    </bndbox>
  </object>
  <object>
    <name>&#1080;</name>
    <pose/>
    <truncated/>
    <difficult/>
    <bndbox>
      <xmin>356.15625</xmin>
      <ymin>418.1762538321396</ymin>
      <xmax>379.21136474609375</xmax>
      <ymax>453.01029924229584</ymax>
    </bndbox>
  </object>
  <object>
    <name>&#1084;</name>
    <pose/>
    <truncated/>
    <difficult/>
    <bndbox>
      <xmin>413.0952453613281</xmin>
      <ymin>417.90724609604825</ymin>
      <xmax>436.1503601074219</xmax>
      <ymax>452.7412915062045</ymax>
    </bndbox>
  </object>
  <object>
    <name>&#1072;</name>
    <pose/>
    <truncated/>
    <difficult/>
    <bndbox>
      <xmin>441.86328125</xmin>
      <ymin>417.7713317871094</ymin>
      <xmax>464.91839599609375</xmax>
      <ymax>452.6053771972656</ymax>
    </bndbox>
  </object>
  <object>
    <name>&#1096;</name>
    <pose/>
    <truncated/>
    <difficult/>
    <bndbox>
      <xmin>468.9456075032552</xmin>
      <ymin>415.4665153288007</ymin>
      <xmax>491.9307352701823</xmax>
      <ymax>452.72217125327984</ymax>
    </bndbox>
  </object>
  <object>
    <name>&#1091;</name>
    <pose/>
    <truncated/>
    <difficult/>
    <bndbox>
      <xmin>497.9007003219039</xmin>
      <ymin>415.17429606119794</ymin>
      <xmax>520.885828088831</xmax>
      <ymax>452.42995198567706</ymax>
    </bndbox>
  </object>
  <object>
    <name>&#1090;</name>
    <pose/>
    <truncated/>
    <difficult/>
    <bndbox>
      <xmin>528.330655698423</xmin>
      <ymin>415.6271000614873</ymin>
      <xmax>551.544502540871</xmax>
      <ymax>452.19714807581016</ymax>
    </bndbox>
  </object>
  <object>
    <name>&#1080;</name>
    <pose/>
    <truncated/>
    <difficult/>
    <bndbox>
      <xmin>92.52087148030598</xmin>
      <ymin>513.6668331460772</ymin>
      <xmax>115.67625681559245</xmax>
      <ymax>548.3221879637855</ymax>
    </bndbox>
  </object>
  <object>
    <name>&#1087;</name>
    <pose/>
    <truncated/>
    <difficult/>
    <bndbox>
      <xmin>151.40226236979166</xmin>
      <ymin>514.0644327799479</ymin>
      <xmax>174.3176472981771</xmax>
      <ymax>548.2806599934896</ymax>
    </bndbox>
  </object>
  <object>
    <name>&#1083;</name>
    <pose/>
    <truncated/>
    <difficult/>
    <bndbox>
      <xmin>179.64905802408853</xmin>
      <ymin>514.1138183798139</ymin>
      <xmax>202.56444295247397</xmax>
      <ymax>548.3300455933556</ymax>
    </bndbox>
  </object>
  <object>
    <name>&#1103;</name>
    <pose/>
    <truncated/>
    <difficult/>
    <bndbox>
      <xmin>209.53866068522134</xmin>
      <ymin>514.166076199612</ymin>
      <xmax>232.45404561360678</xmax>
      <ymax>548.3823034131537</ymax>
    </bndbox>
  </object>
  <object>
    <name>&#1096;</name>
    <pose/>
    <truncated/>
    <difficult/>
    <bndbox>
      <xmin>238.85119120279947</xmin>
      <ymin>514.2173250888991</ymin>
      <xmax>261.7665761311849</xmax>
      <ymax>548.4335523024408</ymax>
    </bndbox>
  </object>
  <object>
    <name>&#1091;</name>
    <pose/>
    <truncated/>
    <difficult/>
    <bndbox>
      <xmin>267.9665018717448</xmin>
      <ymin>514.2682291666666</ymin>
      <xmax>290.8818868001302</xmax>
      <ymax>548.4844563802084</ymax>
    </bndbox>
  </object>
  <object>
    <name>&#1090;</name>
    <pose/>
    <truncated/>
    <difficult/>
    <bndbox>
      <xmin>297.63913981119794</xmin>
      <ymin>514.5035196940104</ymin>
      <xmax>320.9149983723958</xmax>
      <ymax>548.5661824544271</ymax>
    </bndbox>
  </object>
  <object>
    <name>.</name>
    <pose/>
    <truncated/>
    <difficult/>
    <bndbox>
      <xmin>326.56324259440106</xmin>
      <ymin>514.5366554298024</ymin>
      <xmax>349.83910115559894</xmax>
      <ymax>548.5993181902192</ymax>
    </bndbox>
  </object>
  <object>
    <name>&#1072;</name>
    <pose/>
    <truncated/>
    <difficult/>
    <bndbox>
      <xmin>90.01157887776692</xmin>
      <ymin>610.5167400338677</ymin>
      <xmax>113.57185618082683</xmax>
      <ymax>645.4469158151177</ymax>
    </bndbox>
  </object>
  <object>
    <name>&#1089;</name>
    <pose/>
    <truncated/>
    <difficult/>
    <bndbox>
      <xmin>149.98431396484375</xmin>
      <ymin>612.0539416391778</ymin>
      <xmax>173.3193359375</xmax>
      <ymax>646.184109282407</ymax>
    </bndbox>
  </object>
  <object>
    <name>&#1083;</name>
    <pose/>
    <truncated/>
    <difficult/>
    <bndbox>
      <xmin>179.0529810587565</xmin>
      <ymin>612.0297635431367</ymin>
      <xmax>202.52676137288412</xmax>
      <ymax>646.2882677749075</ymax>
    </bndbox>
  </object>
  <object>
    <name>&#1086;</name>
    <pose/>
    <truncated/>
    <difficult/>
    <bndbox>
      <xmin>208.5599619547526</xmin>
      <ymin>612.587890625</ymin>
      <xmax>231.60620625813803</xmax>
      <ymax>645.532958984375</ymax>
    </bndbox>
  </object>
  <object>
    <name>&#1085;</name>
    <pose/>
    <truncated/>
    <difficult/>
    <bndbox>
      <xmin>239.16336059570312</xmin>
      <ymin>612.290283203125</ymin>
      <xmax>262.3151397705078</xmax>
      <ymax>645.8104248046875</ymax>
    </bndbox>
  </object>
  <object>
    <name>&#1080;</name>
    <pose/>
    <truncated/>
    <difficult/>
    <bndbox>
      <xmin>268.6387405395508</xmin>
      <ymin>612.1416090879013</ymin>
      <xmax>291.79051971435547</xmax>
      <ymax>645.6617506894638</ymax>
    </bndbox>
  </object>
  <object>
    <name>&#1093;</name>
    <pose/>
    <truncated/>
    <difficult/>
    <bndbox>
      <xmin>297.94754791259766</xmin>
      <ymin>611.9937751664135</ymin>
      <xmax>321.09932708740234</xmax>
      <ymax>645.513916767976</ymax>
    </bndbox>
  </object>
  <object>
    <name>&#1072;</name>
    <pose/>
    <truncated/>
    <difficult/>
    <bndbox>
      <xmin>328.13269805908203</xmin>
      <ymin>611.8415209630929</ymin>
      <xmax>351.2844772338867</xmax>
      <ymax>645.3616625646554</ymax>
    </bndbox>
  </object>
  <object>
    <name>,</name>
    <pose/>
    <truncated/>
    <difficult/>
    <bndbox>
      <xmin>356.09070587158203</xmin>
      <ymin>611.7005004882812</ymin>
      <xmax>379.2424850463867</xmax>
      <ymax>645.2206420898438</ymax>
    </bndbox>
  </object>
  <object>
    <name>&#1072;</name>
    <pose/>
    <truncated/>
    <difficult/>
    <bndbox>
      <xmin>384.6787109375</xmin>
      <ymin>612.0678506641117</ymin>
      <xmax>407.389892578125</xmax>
      <ymax>644.8847451953617</ymax>
    </bndbox>
  </object>
  <object>
    <name>&#1089;</name>
    <pose/>
    <truncated/>
    <difficult/>
    <bndbox>
      <xmin>442.9390563964844</xmin>
      <ymin>611.877197265625</ymin>
      <xmax>465.6502380371094</xmax>
      <ymax>644.694091796875</ymax>
    </bndbox>
  </object>
  <object>
    <name>&#1083;</name>
    <pose/>
    <truncated/>
    <difficult/>
    <bndbox>
      <xmin>470.94964599609375</xmin>
      <ymin>611.5801595052084</ymin>
      <xmax>493.7713623046875</xmax>
      <ymax>645.1315104166666</ymax>
    </bndbox>
  </object>
  <object>
    <name>&#1086;</name>
    <pose/>
    <truncated/>
    <difficult/>
    <bndbox>
      <xmin>499.9508056640625</xmin>
      <ymin>611.8882783052379</ymin>
      <xmax>522.80859375</xmax>
      <ymax>645.0383840995087</ymax>
    </bndbox>
  </object>
  <object>
    <name>&#1085;</name>
    <pose/>
    <truncated/>
    <difficult/>
    <bndbox>
      <xmin>529.0675048828125</xmin>
      <ymin>611.0075887044271</ymin>
      <xmax>551.92529296875</xmax>
      <ymax>644.1576944986979</ymax>
    </bndbox>
  </object>
  <object>
    <name>&#1080;</name>
    <pose/>
    <truncated/>
    <difficult/>
    <bndbox>
      <xmin>558.0256958007812</xmin>
      <ymin>610.1316934867672</ymin>
      <xmax>580.8834838867188</xmax>
      <ymax>643.2817992810379</ymax>
    </bndbox>
  </object>
  <object>
    <name>&#1093;</name>
    <pose/>
    <truncated/>
    <difficult/>
    <bndbox>
      <xmin>586.7323608398438</xmin>
      <ymin>609.263406144719</ymin>
      <xmax>609.5901489257812</xmax>
      <ymax>642.4135119389898</ymax>
    </bndbox>
  </object>
  <object>
    <name>&#1072;</name>
    <pose/>
    <truncated/>
    <difficult/>
    <bndbox>
      <xmin>615.6474609375</xmin>
      <ymin>608.3888142903646</ymin>
      <xmax>638.5052490234375</xmax>
      <ymax>641.5389200846354</ymax>
    </bndbox>
  </object>
  <object>
    <name>&#1090;</name>
    <pose/>
    <truncated/>
    <difficult/>
    <bndbox>
      <xmin>89.2631009419759</xmin>
      <ymin>709.2975340976263</ymin>
      <xmax>113.04404322306316</xmax>
      <ymax>744.5152261549181</ymax>
    </bndbox>
  </object>
  <object>
    <name>&#1072;</name>
    <pose/>
    <truncated/>
    <difficult/>
    <bndbox>
      <xmin>119.41736857096355</xmin>
      <ymin>709.3446655273438</ymin>
      <xmax>143.32366689046225</xmax>
      <ymax>744.5684204101562</ymax>
    </bndbox>
  </object>
  <object>
    <name>&#1082;</name>
    <pose/>
    <truncated/>
    <difficult/>
    <bndbox>
      <xmin>148.85254542032877</xmin>
      <ymin>709.280124337564</ymin>
      <xmax>172.75884373982748</xmax>
      <ymax>744.5038792203765</ymax>
    </bndbox>
  </object>
  <object>
    <name>&#1086;</name>
    <pose/>
    <truncated/>
    <difficult/>
    <bndbox>
      <xmin>208.74740600585938</xmin>
      <ymin>710.1633053801697</ymin>
      <xmax>232.5936279296875</xmax>
      <ymax>744.986344117149</ymax>
    </bndbox>
  </object>
  <object>
    <name>&#1090;</name>
    <pose/>
    <truncated/>
    <difficult/>
    <bndbox>
      <xmin>238.80281575520834</xmin>
      <ymin>709.9036458333334</ymin>
      <xmax>262.47718302408856</xmax>
      <ymax>744.4054361979166</ymax>
    </bndbox>
  </object>
  <object>
    <name>&#1087;</name>
    <pose/>
    <truncated/>
    <difficult/>
    <bndbox>
      <xmin>268.73529561360675</xmin>
      <ymin>709.4870129479855</ymin>
      <xmax>292.409662882487</xmax>
      <ymax>743.9888033125687</ymax>
    </bndbox>
  </object>
  <object>
    <name>&#1083;</name>
    <pose/>
    <truncated/>
    <difficult/>
    <bndbox>
      <xmin>298.33710225423175</xmin>
      <ymin>709.0749827329636</ymin>
      <xmax>322.011469523112</xmax>
      <ymax>743.5767730975468</ymax>
    </bndbox>
  </object>
  <object>
    <name>&#1103;</name>
    <pose/>
    <truncated/>
    <difficult/>
    <bndbox>
      <xmin>328.0898183186849</xmin>
      <ymin>708.660851996068</ymin>
      <xmax>351.7641855875651</xmax>
      <ymax>743.1626423606513</ymax>
    </bndbox>
  </object>
  <object>
    <name>&#1089;</name>
    <pose/>
    <truncated/>
    <difficult/>
    <bndbox>
      <xmin>358.15802510579425</xmin>
      <ymin>708.2423299153646</ymin>
      <xmax>381.8323923746745</xmax>
      <ymax>742.7441202799479</ymax>
    </bndbox>
  </object>
  <object>
    <name>&#1099;</name>
    <pose/>
    <truncated/>
    <difficult/>
    <bndbox>
      <xmin>387.20875040690106</xmin>
      <ymin>707.8693952448052</ymin>
      <xmax>411.0084737141927</xmax>
      <ymax>742.3772484349095</ymax>
    </bndbox>
  </object>
  <object>
    <name>&#1074;</name>
    <pose/>
    <truncated/>
    <difficult/>
    <bndbox>
      <xmin>415.9195861816406</xmin>
      <ymin>707.8578491210938</ymin>
      <xmax>439.3985290527344</xmax>
      <ymax>742.3413696289062</ymax>
    </bndbox>
  </object>
  <object>
    <name>&#1072;</name>
    <pose/>
    <truncated/>
    <difficult/>
    <bndbox>
      <xmin>443.54869588216144</xmin>
      <ymin>707.7541671165594</ymin>
      <xmax>466.6734110514323</xmax>
      <ymax>741.7324792910387</ymax>
    </bndbox>
  </object>
  <object>
    <name>&#1077;</name>
    <pose/>
    <truncated/>
    <difficult/>
    <bndbox>
      <xmin>472.5797627766927</xmin>
      <ymin>707.4983927408854</ymin>
      <xmax>495.70447794596356</xmax>
      <ymax>741.4767049153646</ymax>
    </bndbox>
  </object>
  <object>
    <name>&#1090;</name>
    <pose/>
    <truncated/>
    <difficult/>
    <bndbox>
      <xmin>501.690185546875</xmin>
      <ymin>707.1913123328446</ymin>
      <xmax>524.1951904296875</xmax>
      <ymax>739.9208859005529</ymax>
    </bndbox>
  </object>
  <object>
    <name>&#1083;</name>
    <pose/>
    <truncated/>
    <difficult/>
    <bndbox>
      <xmin>559.4710693359375</xmin>
      <ymin>706.8844197591146</ymin>
      <xmax>581.97607421875</xmax>
      <ymax>739.6139933268229</ymax>
    </bndbox>
  </object>
  <object>
    <name>&#1080;</name>
    <pose/>
    <truncated/>
    <difficult/>
    <bndbox>
      <xmin>588.559814453125</xmin>
      <ymin>706.7299202210289</ymin>
      <xmax>611.0648193359375</xmax>
      <ymax>739.4594937887372</ymax>
    </bndbox>
  </object>
  <object>
    <name>&#1093;</name>
    <pose/>
    <truncated/>
    <difficult/>
    <bndbox>
      <xmin>617.977783203125</xmin>
      <ymin>706.5736720719601</ymin>
      <xmax>640.4827880859375</xmax>
      <ymax>739.3032456396684</ymax>
    </bndbox>
  </object>
  <object>
    <name>&#1086;</name>
    <pose/>
    <truncated/>
    <difficult/>
    <bndbox>
      <xmin>646.93310546875</xmin>
      <ymin>706.4198811848959</ymin>
      <xmax>669.4381103515625</xmax>
      <ymax>739.1494547526041</ymax>
    </bndbox>
  </object>
  <object>
    <name>,</name>
    <pose/>
    <truncated/>
    <difficult/>
    <bndbox>
      <xmin>672.926513671875</xmin>
      <ymin>706.2818219614925</ymin>
      <xmax>695.4315185546875</xmax>
      <ymax>739.0113955292007</ymax>
    </bndbox>
  </object>
  <object>
    <name>&#1095;</name>
    <pose/>
    <truncated/>
    <difficult/>
    <bndbox>
      <xmin>88.750244140625</xmin>
      <ymin>810.7435709635416</ymin>
      <xmax>112.48095703125</xmax>
      <ymax>845.9971516927084</ymax>
    </bndbox>
  </object>
  <object>
    <name>&#1090;</name>
    <pose/>
    <truncated/>
    <difficult/>
    <bndbox>
      <xmin>118.89044189453125</xmin>
      <ymin>810.4218432838605</ymin>
      <xmax>142.62115478515625</xmax>
      <ymax>845.6754240130273</ymax>
    </bndbox>
  </object>
  <object>
    <name>&#1086;</name>
    <pose/>
    <truncated/>
    <difficult/>
    <bndbox>
      <xmin>149.0318857828776</xmin>
      <ymin>810.2079874674479</ymin>
      <xmax>172.58044942220053</xmax>
      <ymax>845.0338338216146</ymax>
    </bndbox>
  </object>
  <object>
    <name>&#1088;</name>
    <pose/>
    <truncated/>
    <difficult/>
    <bndbox>
      <xmin>208.01539103190103</xmin>
      <ymin>809.4306012907564</ymin>
      <xmax>231.56395467122397</xmax>
      <ymax>844.2564476449231</ymax>
    </bndbox>
  </object>
  <object>
    <name>&#1091;</name>
    <pose/>
    <truncated/>
    <difficult/>
    <bndbox>
      <xmin>238.06747690836588</xmin>
      <ymin>809.0345231661607</ymin>
      <xmax>261.6160405476888</xmax>
      <ymax>843.8603695203275</ymax>
    </bndbox>
  </object>
  <object>
    <name>&#1084;</name>
    <pose/>
    <truncated/>
    <difficult/>
    <bndbox>
      <xmin>268.15000406901044</xmin>
      <ymin>808.6380438339152</ymin>
      <xmax>291.6985677083333</xmax>
      <ymax>843.4638901880819</ymax>
    </bndbox>
  </object>
  <object>
    <name>&#1103;</name>
    <pose/>
    <truncated/>
    <difficult/>
    <bndbox>
      <xmin>298.6082255045573</xmin>
      <ymin>808.2366129557291</ymin>
      <xmax>322.1567891438802</xmax>
      <ymax>843.0624593098959</ymax>
    </bndbox>
  </object>
  <object>
    <name>&#1085;</name>
    <pose/>
    <truncated/>
    <difficult/>
    <bndbox>
      <xmin>328.87060292561847</xmin>
      <ymin>807.4783587249904</ymin>
      <xmax>352.1974512736003</xmax>
      <ymax>841.8144589854071</ymax>
    </bndbox>
  </object>
  <object>
    <name>&#1072;</name>
    <pose/>
    <truncated/>
    <difficult/>
    <bndbox>
      <xmin>358.55419667561847</xmin>
      <ymin>806.7808634440104</ymin>
      <xmax>381.8810450236003</xmax>
      <ymax>841.1169637044271</ymax>
    </bndbox>
  </object>
  <object>
    <name>&#1103;</name>
    <pose/>
    <truncated/>
    <difficult/>
    <bndbox>
      <xmin>387.6760762532552</xmin>
      <ymin>806.506103515625</ymin>
      <xmax>410.68677775065106</xmax>
      <ymax>840.4190673828125</ymax>
    </bndbox>
  </object>
  <object>
    <name>&#1083;</name>
    <pose/>
    <truncated/>
    <difficult/>
    <bndbox>
      <xmin>444.67889912923175</xmin>
      <ymin>805.9060021667456</ymin>
      <xmax>467.4591013590495</xmax>
      <ymax>839.3785770365373</ymax>
    </bndbox>
  </object>
  <object>
    <name>&#1091;</name>
    <pose/>
    <truncated/>
    <difficult/>
    <bndbox>
      <xmin>473.8435414632161</xmin>
      <ymin>805.4621278679983</ymin>
      <xmax>496.6237436930339</xmax>
      <ymax>838.9347027377901</ymax>
    </bndbox>
  </object>
  <object>
    <name>&#1085;</name>
    <pose/>
    <truncated/>
    <difficult/>
    <bndbox>
      <xmin>503.0779622395833</xmin>
      <ymin>805.0171915690104</ymin>
      <xmax>525.858164469401</xmax>
      <ymax>838.4897664388021</ymax>
    </bndbox>
  </object>
  <object>
    <name>&#1072;</name>
    <pose/>
    <truncated/>
    <difficult/>
    <bndbox>
      <xmin>531.5278981526693</xmin>
      <ymin>804.5495471807014</ymin>
      <xmax>554.2120920817057</xmax>
      <ymax>838.1153023890347</ymax>
    </bndbox>
  </object>
  <object>
    <name>&#1074;</name>
    <pose/>
    <truncated/>
    <difficult/>
    <bndbox>
      <xmin>87.21127065022786</xmin>
      <ymin>914.7955118815104</ymin>
      <xmax>111.21571604410808</xmax>
      <ymax>948.1595662434896</ymax>
    </bndbox>
  </object>
  <object>
    <name>&#1085;</name>
    <pose/>
    <truncated/>
    <difficult/>
    <bndbox>
      <xmin>148.46473693847656</xmin>
      <ymin>912.5014241536459</ymin>
      <xmax>171.8918914794922</xmax>
      <ymax>946.1238199869791</ymax>
    </bndbox>
  </object>
  <object>
    <name>&#1077;</name>
    <pose/>
    <truncated/>
    <difficult/>
    <bndbox>
      <xmin>177.56825256347656</xmin>
      <ymin>912.0717600992357</ymin>
      <xmax>200.9954071044922</xmax>
      <ymax>945.694155932569</ymax>
    </bndbox>
  </object>
  <object>
    <name>&#1073;</name>
    <pose/>
    <truncated/>
    <difficult/>
    <bndbox>
      <xmin>207.51333618164062</xmin>
      <ymin>911.6296717205389</ymin>
      <xmax>230.94049072265625</xmax>
      <ymax>945.2520675538722</ymax>
    </bndbox>
  </object>
  <object>
    <name>&#1077;</name>
    <pose/>
    <truncated/>
    <difficult/>
    <bndbox>
      <xmin>237.53685760498047</xmin>
      <ymin>911.1864253406637</ymin>
      <xmax>260.9640121459961</xmax>
      <ymax>944.808821173997</ymax>
    </bndbox>
  </object>
  <object>
    <name>&#1079;</name>
    <pose/>
    <truncated/>
    <difficult/>
    <bndbox>
      <xmin>298.7983856201172</xmin>
      <ymin>910.2820027669271</ymin>
      <xmax>322.2255401611328</xmax>
      <ymax>943.9043986002604</ymax>
    </bndbox>
  </object>
  <object>
    <name>&#1072;</name>
    <pose/>
    <truncated/>
    <difficult/>
    <bndbox>
      <xmin>329.14637247721356</xmin>
      <ymin>909.2760009765625</ymin>
      <xmax>352.30894978841144</xmax>
      <ymax>941.686767578125</ymax>
    </bndbox>
  </object>
  <object>
    <name>&#1076;</name>
    <pose/>
    <truncated/>
    <difficult/>
    <bndbox>
      <xmin>360.20777384440106</xmin>
      <ymin>908.7597045898438</ymin>
      <xmax>382.4032491048177</xmax>
      <ymax>940.4457397460938</ymax>
    </bndbox>
  </object>
  <object>
    <name>&#1088;</name>
    <pose/>
    <truncated/>
    <difficult/>
    <bndbox>
      <xmin>389.02158610026044</xmin>
      <ymin>908.2033958388731</ymin>
      <xmax>411.21706136067706</xmax>
      <ymax>939.8894309951231</ymax>
    </bndbox>
  </object>
  <object>
    <name>&#1086;</name>
    <pose/>
    <truncated/>
    <difficult/>
    <bndbox>
      <xmin>417.7089131673177</xmin>
      <ymin>908.2383015950521</ymin>
      <xmax>439.6106669108073</xmax>
      <ymax>939.6640421549479</ymax>
    </bndbox>
  </object>
  <object>
    <name>&#1078;</name>
    <pose/>
    <truncated/>
    <difficult/>
    <bndbox>
      <xmin>446.2638753255208</xmin>
      <ymin>907.4587475145483</ymin>
      <xmax>468.16562906901044</xmax>
      <ymax>938.8844880744441</ymax>
    </bndbox>
  </object>
  <object>
    <name>&#1072;</name>
    <pose/>
    <truncated/>
    <difficult/>
    <bndbox>
      <xmin>475.3941243489583</xmin>
      <ymin>906.6634880298219</ymin>
      <xmax>497.29587809244794</xmax>
      <ymax>938.0892285897177</ymax>
    </bndbox>
  </object>
  <object>
    <name>&#1083;</name>
    <pose/>
    <truncated/>
    <difficult/>
    <bndbox>
      <xmin>504.2017110188802</xmin>
      <ymin>905.8770372681788</ymin>
      <xmax>526.1034647623698</xmax>
      <ymax>937.3027778280746</ymax>
    </bndbox>
  </object>
  <object>
    <name>&#1072;</name>
    <pose/>
    <truncated/>
    <difficult/>
    <bndbox>
      <xmin>532.2085469563802</xmin>
      <ymin>905.1124471028646</ymin>
      <xmax>554.1103006998698</xmax>
      <ymax>936.5381876627604</ymax>
    </bndbox>
  </object>
  <object>
    <name>&#1080;</name>
    <pose/>
    <truncated/>
    <difficult/>
    <bndbox>
      <xmin>86.07614390055339</xmin>
      <ymin>1015.3263083612349</ymin>
      <xmax>109.24577077229817</xmax>
      <ymax>1050.8628684198286</ymax>
    </bndbox>
  </object>
  <object>
    <name>&#1085;</name>
    <pose/>
    <truncated/>
    <difficult/>
    <bndbox>
      <xmin>148.39533487955728</xmin>
      <ymin>1014.0481567382812</ymin>
      <xmax>171.5649617513021</xmax>
      <ymax>1049.584716796875</ymax>
    </bndbox>
  </object>
  <object>
    <name>&#1072;</name>
    <pose/>
    <truncated/>
    <difficult/>
    <bndbox>
      <xmin>175.984130859375</xmin>
      <ymin>1013.3014526367188</ymin>
      <xmax>199.16372680664062</xmax>
      <ymax>1048.2601318359375</ymax>
    </bndbox>
  </object>
  <object>
    <name>&#1073;</name>
    <pose/>
    <truncated/>
    <difficult/>
    <bndbox>
      <xmin>236.27027384440103</xmin>
      <ymin>1012.3952494741342</ymin>
      <xmax>259.72215779622394</xmax>
      <ymax>1047.45233769028</ymax>
    </bndbox>
  </object>
  <object>
    <name>&#1077;</name>
    <pose/>
    <truncated/>
    <difficult/>
    <bndbox>
      <xmin>266.43299357096356</xmin>
      <ymin>1013.0887045981341</ymin>
      <xmax>290.14769490559894</xmax>
      <ymax>1047.9399415773007</ymax>
    </bndbox>
  </object>
  <object>
    <name>&#1076;</name>
    <pose/>
    <truncated/>
    <difficult/>
    <bndbox>
      <xmin>297.70105997721356</xmin>
      <ymin>1012.150400797526</ymin>
      <xmax>321.41576131184894</xmax>
      <ymax>1047.0016377766926</ymax>
    </bndbox>
  </object>
  <object>
    <name>&#1085;</name>
    <pose/>
    <truncated/>
    <difficult/>
    <bndbox>
      <xmin>327.3004862467448</xmin>
      <ymin>1011.262170172591</ymin>
      <xmax>351.0151875813802</xmax>
      <ymax>1046.1134071517577</ymax>
    </bndbox>
  </object>
  <object>
    <name>&#1086;</name>
    <pose/>
    <truncated/>
    <difficult/>
    <bndbox>
      <xmin>358.75510660807294</xmin>
      <ymin>1010.3182681913089</ymin>
      <xmax>382.4698079427083</xmax>
      <ymax>1045.1695051704755</ymax>
    </bndbox>
  </object>
  <object>
    <name>&#1075;</name>
    <pose/>
    <truncated/>
    <difficult/>
    <bndbox>
      <xmin>388.8926493326823</xmin>
      <ymin>1009.4138895670573</ymin>
      <xmax>412.6073506673177</xmax>
      <ymax>1044.2651265462239</ymax>
    </bndbox>
  </object>
  <object>
    <name>&#1086;</name>
    <pose/>
    <truncated/>
    <difficult/>
    <bndbox>
      <xmin>417.23887125651044</xmin>
      <ymin>1008.5632655656096</ymin>
      <xmax>440.9535725911458</xmax>
      <ymax>1043.4145025447763</ymax>
    </bndbox>
  </object>
  <object>
    <name>&#1083;</name>
    <pose/>
    <truncated/>
    <difficult/>
    <bndbox>
      <xmin>506.45161290322585</xmin>
      <ymin>1007.7419354838709</ymin>
      <xmax>530.3225806451612</xmax>
      <ymax>1043.225806451613</ymax>
    </bndbox>
  </object>
  <object>
    <name>&#1089;</name>
    <pose/>
    <truncated/>
    <difficult/>
    <bndbox>
      <xmin>476.7741935483871</xmin>
      <ymin>1008.3870967741935</ymin>
      <xmax>499.1759394163725</xmax>
      <ymax>1041.2381266932332</ymax>
    </bndbox>
  </object>
  <object>
    <name>&#1085;</name>
    <pose/>
    <truncated/>
    <difficult/>
    <bndbox>
      <xmin>567.234113139491</xmin>
      <ymin>1007.2116801491691</ymin>
      <xmax>589.6774193548388</xmax>
      <ymax>1042.5806451612902</ymax>
    </bndbox>
  </object>
  <object>
    <name>&#1072;</name>
    <pose/>
    <truncated/>
    <difficult/>
    <bndbox>
      <xmin>595.6033935546875</xmin>
      <ymin>1005.925791422526</ymin>
      <xmax>618.0645161290322</xmax>
      <ymax>1043.225806451613</ymax>
    </bndbox>
  </object>
  <object>
    <name>&#1082;</name>
    <pose/>
    <truncated/>
    <difficult/>
    <bndbox>
      <xmin>85.96268463134766</xmin>
      <ymin>1123.2959391276042</ymin>
      <xmax>109.03225806451613</xmax>
      <ymax>1160.0</ymax>
    </bndbox>
  </object>
  <object>
    <name>&#1091;</name>
    <pose/>
    <truncated/>
    <difficult/>
    <bndbox>
      <xmin>116.64938100179036</xmin>
      <ymin>1120.5389404296875</ymin>
      <xmax>140.6451612903226</xmax>
      <ymax>1159.3548387096773</ymax>
    </bndbox>
  </object>
  <object>
    <name>&#1073;</name>
    <pose/>
    <truncated/>
    <difficult/>
    <bndbox>
      <xmin>146.9240734961725</xmin>
      <ymin>1120.6636971609285</ymin>
      <xmax>169.6774193548387</xmax>
      <ymax>1157.4193548387098</ymax>
    </bndbox>
  </object>
  <object>
    <name>&#1072;</name>
    <pose/>
    <truncated/>
    <difficult/>
    <bndbox>
      <xmin>175.97573778706214</xmin>
      <ymin>1120.0115559895833</ymin>
      <xmax>199.3548387096774</xmax>
      <ymax>1156.774193548387</ymax>
    </bndbox>
  </object>
  <object>
    <name>&#1088;</name>
    <pose/>
    <truncated/>
    <difficult/>
    <bndbox>
      <xmin>208.68177541097006</xmin>
      <ymin>1117.1678932213865</ymin>
      <xmax>233.3280512491862</xmax>
      <ymax>1154.974452466178</ymax>
    </bndbox>
  </object>
  <object>
    <name>&#1077;</name>
    <pose/>
    <truncated/>
    <difficult/>
    <bndbox>
      <xmin>236.58586629231772</xmin>
      <ymin>1116.5286051432292</ymin>
      <xmax>261.2321421305339</xmax>
      <ymax>1154.3351643880208</ymax>
    </bndbox>
  </object>
  <object>
    <name>&#1084;</name>
    <pose/>
    <truncated/>
    <difficult/>
    <bndbox>
      <xmin>268.3917541503906</xmin>
      <ymin>1116.3391520182292</ymin>
      <xmax>292.1354675292969</xmax>
      <ymax>1153.3026936848958</ymax>
    </bndbox>
  </object>
  <object>
    <name>&#1091;</name>
    <pose/>
    <truncated/>
    <difficult/>
    <bndbox>
      <xmin>329.2489013671875</xmin>
      <ymin>1114.8892025070822</ymin>
      <xmax>352.99261474609375</xmax>
      <ymax>1151.8527441737488</ymax>
    </bndbox>
  </object>
  <object>
    <name>&#1087;</name>
    <pose/>
    <truncated/>
    <difficult/>
    <bndbox>
      <xmin>359.6552429199219</xmin>
      <ymin>1114.1647574404562</ymin>
      <xmax>383.3989562988281</xmax>
      <ymax>1151.1282991071228</ymax>
    </bndbox>
  </object>
  <object>
    <name>&#1072;</name>
    <pose/>
    <truncated/>
    <difficult/>
    <bndbox>
      <xmin>389.8542175292969</xmin>
      <ymin>1113.4452529865912</ymin>
      <xmax>413.5979309082031</xmax>
      <ymax>1150.4087946532577</ymax>
    </bndbox>
  </object>
  <object>
    <name>&#1083;</name>
    <pose/>
    <truncated/>
    <difficult/>
    <bndbox>
      <xmin>418.6749572753906</xmin>
      <ymin>1112.7585856119792</ymin>
      <xmax>442.4186706542969</xmax>
      <ymax>1149.7221272786458</ymax>
    </bndbox>
  </object>
  <object>
    <name>&#1072;</name>
    <pose/>
    <truncated/>
    <difficult/>
    <bndbox>
      <xmin>448.46929931640625</xmin>
      <ymin>1113.7412571229536</ymin>
      <xmax>470.9896240234375</xmax>
      <ymax>1148.744268190662</ymax>
    </bndbox>
  </object>
  <object>
    <name>.</name>
    <pose/>
    <truncated/>
    <difficult/>
    <bndbox>
      <xmin>477.657470703125</xmin>
      <ymin>1113.6253255208333</ymin>
      <xmax>500.17779541015625</xmax>
      <ymax>1148.6283365885417</ymax>
    </bndbox>
  </object>
  <object>
    <name>&#1074;</name>
    <pose/>
    <truncated/>
    <difficult/>
    <bndbox>
      <xmin>85.36844253540039</xmin>
      <ymin>1226.0698649088542</ymin>
      <xmax>109.93655014038086</xmax>
      <ymax>1263.9721272786458</ymax>
    </bndbox>
  </object>
  <object>
    <name>&#1086;</name>
    <pose/>
    <truncated/>
    <difficult/>
    <bndbox>
      <xmin>116.94143676757812</xmin>
      <ymin>1225.4831136067708</ymin>
      <xmax>141.0573501586914</xmax>
      <ymax>1263.3396402994792</ymax>
    </bndbox>
  </object>
  <object>
    <name>&#1090;</name>
    <pose/>
    <truncated/>
    <difficult/>
    <bndbox>
      <xmin>147.31963729858398</xmin>
      <ymin>1224.5563984705511</ymin>
      <xmax>171.43555068969727</xmax>
      <ymax>1262.4129251632596</ymax>
    </bndbox>
  </object>
  <object>
    <name>&#1073;</name>
    <pose/>
    <truncated/>
    <difficult/>
    <bndbox>
      <xmin>207.05065536499023</xmin>
      <ymin>1222.734248455857</ymin>
      <xmax>231.16656875610352</xmax>
      <ymax>1260.5907751485654</ymax>
    </bndbox>
  </object>
  <object>
    <name>&#1099;</name>
    <pose/>
    <truncated/>
    <difficult/>
    <bndbox>
      <xmin>237.29160690307617</xmin>
      <ymin>1221.8117202272533</ymin>
      <xmax>261.40752029418945</xmax>
      <ymax>1259.6682469199618</ymax>
    </bndbox>
  </object>
  <object>
    <name>&#1083;</name>
    <pose/>
    <truncated/>
    <difficult/>
    <bndbox>
      <xmin>268.0951499938965</xmin>
      <ymin>1220.8720296223958</ymin>
      <xmax>292.21106338500977</xmax>
      <ymax>1258.7285563151042</ymax>
    </bndbox>
  </object>
  <object>
    <name>&#1072;</name>
    <pose/>
    <truncated/>
    <difficult/>
    <bndbox>
      <xmin>298.4661000569661</xmin>
      <ymin>1220.1772524097235</ymin>
      <xmax>322.2292124430339</xmax>
      <ymax>1257.619960743057</ymax>
    </bndbox>
  </object>
  <object>
    <name>&#1087;</name>
    <pose/>
    <truncated/>
    <difficult/>
    <bndbox>
      <xmin>359.46991475423175</xmin>
      <ymin>1218.3182383249405</ymin>
      <xmax>383.2330271402995</xmax>
      <ymax>1255.760946658274</ymax>
    </bndbox>
  </object>
  <object>
    <name>&#1086;</name>
    <pose/>
    <truncated/>
    <difficult/>
    <bndbox>
      <xmin>390.0191701253255</xmin>
      <ymin>1217.3872884114583</ymin>
      <xmax>413.78228251139325</xmax>
      <ymax>1254.8299967447917</ymax>
    </bndbox>
  </object>
  <object>
    <name>&#1090;</name>
    <pose/>
    <truncated/>
    <difficult/>
    <bndbox>
      <xmin>419.56427001953125</xmin>
      <ymin>1216.3942906797263</ymin>
      <xmax>443.23876953125</xmax>
      <ymax>1254.0339391172263</ymax>
    </bndbox>
  </object>
  <object>
    <name>&#1086;</name>
    <pose/>
    <truncated/>
    <difficult/>
    <bndbox>
      <xmin>449.3856709798177</xmin>
      <ymin>1216.4756266276042</ymin>
      <xmax>472.7997538248698</xmax>
      <ymax>1253.6442464192708</ymax>
    </bndbox>
  </object>
  <object>
    <name>&#1084;</name>
    <pose/>
    <truncated/>
    <difficult/>
    <bndbox>
      <xmin>478.18846638997394</xmin>
      <ymin>1213.3579508463542</ymin>
      <xmax>502.90210978190106</xmax>
      <ymax>1252.9040120442708</ymax>
    </bndbox>
  </object>
  <object>
    <name>&#1079;</name>
    <pose/>
    <truncated/>
    <difficult/>
    <bndbox>
      <xmin>539.691423969884</xmin>
      <ymin>1214.164309553032</ymin>
      <xmax>563.8709677419355</xmax>
      <ymax>1250.3225806451612</ymax>
    </bndbox>
  </object>
  <object>
    <name>&#1072;</name>
    <pose/>
    <truncated/>
    <difficult/>
    <bndbox>
      <xmin>569.291259765625</xmin>
      <ymin>1213.3169352213542</ymin>
      <xmax>593.5483870967741</xmax>
      <ymax>1250.3225806451612</ymax>
    </bndbox>
  </object>
  <object>
    <name>&#1073;</name>
    <pose/>
    <truncated/>
    <difficult/>
    <bndbox>
      <xmin>600.2061124411963</xmin>
      <ymin>1212.158405262937</ymin>
      <xmax>624.516129032258</xmax>
      <ymax>1249.032258064516</ymax>
    </bndbox>
  </object>
  <object>
    <name>&#1086;</name>
    <pose/>
    <truncated/>
    <difficult/>
    <bndbox>
      <xmin>628.9300720871136</xmin>
      <ymin>1212.035449011438</ymin>
      <xmax>653.5483870967741</xmax>
      <ymax>1248.3870967741934</ymax>
    </bndbox>
  </object>
  <object>
    <name>&#1090;</name>
    <pose/>
    <truncated/>
    <difficult/>
    <bndbox>
      <xmin>659.2876160324261</xmin>
      <ymin>1210.6133855165249</ymin>
      <xmax>683.2258064516129</xmax>
      <ymax>1247.741935483871</ymax>
    </bndbox>
  </object>
  <object>
    <name>&#1072;</name>
    <pose/>
    <truncated/>
    <difficult/>
    <bndbox>
      <xmin>687.8912320701025</xmin>
      <ymin>1210.5595522524918</ymin>
      <xmax>712.258064516129</xmax>
      <ymax>1247.741935483871</ymax>
    </bndbox>
  </object>
  <object>
    <name>-</name>
    <pose/>
    <truncated/>
    <difficult/>
    <bndbox>
      <xmin>718.0645161290322</xmin>
      <ymin>1210.3225806451612</ymin>
      <xmax>743.2258064516129</xmax>
      <ymax>1247.741935483871</ymax>
    </bndbox>
  </object>
  <object>
    <name>&#1096;</name>
    <pose/>
    <truncated/>
    <difficult/>
    <bndbox>
      <xmin>382.25798995406535</xmin>
      <ymin>225.21596470585575</ymin>
      <xmax>405.3021183720341</xmax>
      <ymax>260.5144876550745</ymax>
    </bndbox>
  </object>
  <object>
    <name>&#1080;</name>
    <pose/>
    <truncated/>
    <difficult/>
    <bndbox>
      <xmin>409.97298431396484</xmin>
      <ymin>224.58757816580797</ymin>
      <xmax>433.0171127319336</xmax>
      <ymax>259.88610111502675</ymax>
    </bndbox>
  </object>
  <object>
    <name>&#1084;</name>
    <pose/>
    <truncated/>
    <difficult/>
    <bndbox>
      <xmin>322.9987306948061</xmin>
      <ymin>224.29003877992983</ymin>
      <xmax>346.04285911277486</xmax>
      <ymax>259.5885617291486</ymax>
    </bndbox>
  </object>
  <object>
    <name>&#1099;</name>
    <pose/>
    <truncated/>
    <difficult/>
    <bndbox>
      <xmin>352.4802121762876</xmin>
      <ymin>224.14189063178168</ymin>
      <xmax>375.52434059425633</xmax>
      <ymax>259.4404135810004</ymax>
    </bndbox>
  </object>
  <object>
    <name>&#1086;</name>
    <pose/>
    <truncated/>
    <difficult/>
    <bndbox>
      <xmin>536.7096774193549</xmin>
      <ymin>1007.032258064516</ymin>
      <xmax>560.5806451612902</xmax>
      <ymax>1042.516129032258</ymax>
    </bndbox>
  </object>
</annotation>
